printutil/__init__.py
printutil-0.0.3.dist-info/LICENSE
printutil-0.0.3.dist-info/METADATA
printutil-0.0.3.dist-info/WHEEL
printutil-0.0.3.dist-info/top_level.txt
printutil-0.0.3.dist-info/RECORD
